messenger_bot/__init__.py
messenger_bot/buttons/button_generator.py
messenger_bot/buttons/button_validator.py
messenger_bot/template/template_button.py
messenger_bot/template/template_generic.py
messenger_bot/template/template_list.py
messenger_bot/template/template_quick_reply.py
messenger_bot/utility/base.py
messenger_bot/utility/tag.py
messenger_bot/utility/util.py
messenger_bot_library-2.0.3b0.dist-info/LICENSE.txt
messenger_bot_library-2.0.3b0.dist-info/METADATA
messenger_bot_library-2.0.3b0.dist-info/WHEEL
messenger_bot_library-2.0.3b0.dist-info/entry_points.txt
messenger_bot_library-2.0.3b0.dist-info/top_level.txt
messenger_bot_library-2.0.3b0.dist-info/RECORD
