Metadata-Version: 2.1
Name: messenger-bot-library
Version: 2.0.3b0
Summary: A python package that helps you to create payload for facebook messenger bot.
Home-page: https://github.com/p1r-a-t3/Messenger-Bot-Library
Author: p1r-a-t3
Author-email: ibtehaz.92@gmail.com
License: MIT
Platform: UNKNOWN
Classifier: Programming Language :: Python :: 3
Classifier: License :: OSI Approved :: MIT License
Classifier: Operating System :: OS Independent
Requires-Dist: phonenumbers
Requires-Dist: pyfiglet
